{
    "Edges": [
        {
            "src": 0,
            "dest": 1,
            "weight": 1.2
        },
        {
            "src": 0,
            "dest": 2,
            "weight": 1.0
        },
        {
            "src": 1,
            "dest": 0,
            "weight": 1.0
        },
        {
            "src": 2,
            "dest": 3,
            "weight": 1.0
        },
        {
            "src": 3,
            "dest": 2,
            "weight": 1.0
        }
    ],
    "Nodes": [
        {
            "pos": null,
            "id": 0
        },
        {
            "pos": null,
            "id": 1
        },
        {
            "pos": null,
            "id": 2
        },
        {
            "pos": null,
            "id": 3
        },
        {
            "pos": null,
            "id": 4
        }
    ]
}